youtube_simple_scraper/__init__.py
youtube_simple_scraper/continuation_token.py
youtube_simple_scraper/counters.py
youtube_simple_scraper/entities.py
youtube_simple_scraper/list_short.py
youtube_simple_scraper/list_video_comments.py
youtube_simple_scraper/list_videos.py
youtube_simple_scraper/list_videos_request.py
youtube_simple_scraper/logger.py
youtube_simple_scraper/network.py
youtube_simple_scraper/stop_conditions.py
youtube_simple_scraper/proto/__init__.py
youtube_simple_scraper/proto/continuation.py
youtube_simple_scraper-0.0.8.dist-info/LICENCE
youtube_simple_scraper-0.0.8.dist-info/METADATA
youtube_simple_scraper-0.0.8.dist-info/WHEEL
youtube_simple_scraper-0.0.8.dist-info/top_level.txt
youtube_simple_scraper-0.0.8.dist-info/RECORD
